racerapi/__init__.py
racerapi/__main__.py
racerapi/version.py
racerapi/cmd/__init__.py
racerapi/cmd/dev_cmd.py
racerapi/cmd/doctor_cmd.py
racerapi/cmd/env_cmd.py
racerapi/cmd/eval_cmd.py
racerapi/cmd/format_cmd.py
racerapi/cmd/new_cmd.py
racerapi/cmd/routes_cmd.py
racerapi/cmd/test_cmd.py
racerapi/cmd/trace_cmd.py
racerapi/cmd/version_cmd.py
racerapi/cmd/ai/create.py
racerapi/cmd/ai/docs.py
racerapi/cmd/ai/generate_crud.py
racerapi/cmd/ai/generate_module.py
racerapi/cmd/ai/test_generate.py
racerapi/cmd/config/config_cmd.py
racerapi/cmd/generate/__init__.py
racerapi/cmd/generate/base.py
racerapi/cmd/generate/consumer.py
racerapi/cmd/generate/controller.py
racerapi/cmd/generate/event.py
racerapi/cmd/generate/job.py
racerapi/cmd/generate/resource.py
racerapi/cmd/generate/schema.py
racerapi/cmd/generate/service.py
racerapi/core/__init__.py
racerapi/core/app_factory.py
racerapi/core/application.py
racerapi/core/container.py
racerapi/core/controller.py
racerapi/core/decorators.py
racerapi/core/lifecycle.py
racerapi/core/middleware.py
racerapi/core/middleware_adapter.py
racerapi/core/module_loader.py
racerapi/core/plugins.py
racerapi/core/register_middleware.py
racerapi/core/registry.py
racerapi/core/settings.py
racerapi/templates/consumer/consumer.py.jinja
racerapi/templates/controller/controller.py.jinja
racerapi/templates/event/event.py.jinja
racerapi/templates/job/job.py.jinja
racerapi/templates/project/README.md
racerapi/templates/project/main.py
racerapi/templates/project/pyproject.toml
racerapi/templates/project/app/__init__.py
racerapi/templates/project/app/core/__init__.py
racerapi/templates/project/app/core/config.py
racerapi/templates/project/app/core/exceptions.py
racerapi/templates/project/app/core/logging.py
racerapi/templates/project/app/core/response.py
racerapi/templates/project/app/modules/__init__.py
racerapi/templates/project/app/modules/system/__init__.py
racerapi/templates/project/app/modules/system/controller.py
racerapi-0.0.4.dist-info/licenses/LICENSE.md
racerapi-0.0.4.dist-info/METADATA
racerapi-0.0.4.dist-info/WHEEL
racerapi-0.0.4.dist-info/entry_points.txt
racerapi-0.0.4.dist-info/top_level.txt
racerapi-0.0.4.dist-info/RECORD
