Metadata-Version: 2.4
Name: racerapi
Version: 0.0.4
Summary: RacerAPI - Opinionated Backend Framework on Top of FastAPI
Home-page: https://github.com/23bg/racerapi
Author: Prathamesh More
Author-email: "Mr. Prathamesh More" <iamprathamshmore07@gmail.com>
License: MIT
Project-URL: Homepage, https://github.com/your-org/racerapi
Project-URL: Documentation, https://github.com/your-org/racerapi#readme
Classifier: Development Status :: 3 - Alpha
Classifier: Programming Language :: Python :: 3
Classifier: Programming Language :: Python :: 3.10
Classifier: Programming Language :: Python :: 3.11
Classifier: License :: OSI Approved :: MIT License
Classifier: Operating System :: OS Independent
Classifier: Intended Audience :: Developers
Classifier: Framework :: FastAPI
Classifier: Topic :: Software Development :: Libraries :: Application Frameworks
Requires-Python: >=3.10
License-File: LICENSE.md
Requires-Dist: fastapi>=0.115
Requires-Dist: uvicorn[standard]>=0.30
Requires-Dist: typer>=0.9
Requires-Dist: pydantic>=2.6
Requires-Dist: pydantic-settings>=2.2
Provides-Extra: dev
Requires-Dist: pytest>=8.0; extra == "dev"
Requires-Dist: pytest-cov>=4.0; extra == "dev"
Requires-Dist: black>=24.0; extra == "dev"
Requires-Dist: ruff>=0.4.0; extra == "dev"
Requires-Dist: mypy>=1.9.0; extra == "dev"
Requires-Dist: pre-commit>=3.7.0; extra == "dev"
Requires-Dist: python-dotenv>=1.0.0; extra == "dev"
Provides-Extra: ai
Requires-Dist: openai>=1.0.0; extra == "ai"
Dynamic: license-file
